pypixelart/__init__.py
pypixelart/classes.py
pypixelart/constants.py
pypixelart/main.py
pypixelart/utils.py
pypixelart/assets/fonts/OFL.txt
pypixelart/assets/fonts/PressStart2P-Regular.ttf
pypixelart-0.1.2.dist-info/LICENSE
pypixelart-0.1.2.dist-info/METADATA
pypixelart-0.1.2.dist-info/WHEEL
pypixelart-0.1.2.dist-info/entry_points.txt
pypixelart-0.1.2.dist-info/top_level.txt
pypixelart-0.1.2.dist-info/RECORD
