Metadata-Version: 2.1
Name: pypixelart
Version: 0.1.2
Summary: A keyboard-centered approach to pixel art
Home-page: https://github.com/douglascdev/pypixelart
Author: Douglas C.
Author-email: douglasc.dev@gmail.com
License: MIT license
Keywords: pypixelart,pygame,image-editor,pixel-art
Platform: UNKNOWN
Classifier: Development Status :: 2 - Pre-Alpha
Classifier: Intended Audience :: End Users/Desktop
Classifier: License :: OSI Approved :: MIT License
Classifier: Natural Language :: English
Classifier: Programming Language :: Python :: 3
Classifier: Programming Language :: Python :: 3.6
Classifier: Programming Language :: Python :: 3.7
Classifier: Programming Language :: Python :: 3.8
Classifier: Programming Language :: Python :: 3.9
Requires-Python: >=3.6
License-File: LICENSE
Requires-Dist: click (==8.0.1)
Requires-Dist: pygame (==2.0.1)
